CHANGELOG.txt
LICENCE.txt
MANIFEST.in
README.txt
setup.py
bmi_calculator/__init__.py
bmi_calculator/bmi_calculator.py
shekhar_bmi_calculator.egg-info/PKG-INFO
shekhar_bmi_calculator.egg-info/SOURCES.txt
shekhar_bmi_calculator.egg-info/dependency_links.txt
shekhar_bmi_calculator.egg-info/top_level.txt