Metadata-Version: 2.1
Name: shekhar-bmi-calculator
Version: 0.0.3
Summary: A very basic BMI calculator
Home-page: 
Author: Sarvesh Shekhar
Author-email: x22129880@student.ncirl.ie
License: MIT
Keywords: bmi calculator
Classifier: Development Status :: 5 - Production/Stable
Classifier: Intended Audience :: Education
Classifier: Operating System :: Microsoft :: Windows :: Windows 10
Classifier: License :: OSI Approved :: MIT License
Classifier: Programming Language :: Python :: 3.8
License-File: LICENCE.txt
